megatron_mcp/__init__.py
megatron_mcp/chunker.py
megatron_mcp/cli.py
megatron_mcp/indexer.py
megatron_mcp/live_indexer.py
megatron_mcp/mcp_server.py
megatron_mcp/parser.py
megatron_mcp/project_memory.py
megatron_mcp/retriever.py
megatron_mcp/understanding.py
megatron_mcp-0.1.0.dist-info/licenses/LICENSE
megatron_mcp-0.1.0.dist-info/METADATA
megatron_mcp-0.1.0.dist-info/WHEEL
megatron_mcp-0.1.0.dist-info/entry_points.txt
megatron_mcp-0.1.0.dist-info/top_level.txt
megatron_mcp-0.1.0.dist-info/RECORD
