Metadata-Version: 2.4
Name: megatron-mcp
Version: 0.1.0
Summary: Semantic memory for Claude Code sessions
Author: astrosteveo
License-Expression: MIT
Project-URL: Homepage, https://github.com/astrosteveo/megatron
Project-URL: Repository, https://github.com/astrosteveo/megatron
Keywords: claude,claude-code,mcp,memory,semantic-search
Classifier: Development Status :: 4 - Beta
Classifier: Intended Audience :: Developers
Classifier: Programming Language :: Python :: 3
Classifier: Programming Language :: Python :: 3.10
Classifier: Programming Language :: Python :: 3.11
Classifier: Programming Language :: Python :: 3.12
Requires-Python: >=3.10
License-File: LICENSE
Requires-Dist: chromadb>=0.4.0
Requires-Dist: sentence-transformers>=2.2.0
Requires-Dist: click>=8.0.0
Dynamic: license-file
